greetme_paramveer/__init__.py
greetme_paramveer-0.1.1.dist-info/METADATA
greetme_paramveer-0.1.1.dist-info/WHEEL
greetme_paramveer-0.1.1.dist-info/top_level.txt
greetme_paramveer-0.1.1.dist-info/RECORD
