Metadata-Version: 2.4
Name: greetme_paramveer
Version: 0.1.1
Summary: A simple greeting package
Author: Paramveer Singh
Author-email: paramveer.yaduvanshi@gmail.com
License: MIT
Classifier: Programming Language :: Python :: 3
Classifier: License :: OSI Approved :: MIT License
Requires-Python: >=3.6
Dynamic: author
Dynamic: author-email
Dynamic: classifier
Dynamic: description
Dynamic: description-content-type
Dynamic: license
Dynamic: requires-python
Dynamic: summary
